centerline_width/__init__.py
centerline_width/centerline.py
centerline_width/channelMigration.py
centerline_width/error_handling.py
centerline_width/getCoordinatesKML.py
centerline_width/plotDiagrams.py
centerline_width/preprocessing.py
centerline_width/relativeDistance.py
centerline_width/riverAsymmetry.py
centerline_width/riverCenterlineClass.py
centerline_width/riverFeatures.py
centerline_width/saveOutput.py
centerline_width/width.py
centerline_width-2.0.1.dist-info/licenses/LICENSE
centerline_width-2.0.1.dist-info/METADATA
centerline_width-2.0.1.dist-info/WHEEL
centerline_width-2.0.1.dist-info/top_level.txt
centerline_width-2.0.1.dist-info/RECORD
