Metadata-Version: 2.4
Name: centerline-width
Version: 2.0.1
Summary: A Python package to find the centerline and width of rivers based on the latitude and longitude of the right and left bank
Author-email: Cora Schneck <cyschneck@gmail.com>, Una Schneck <ugschneck@gmail.com>
License: MIT License
Project-URL: Issues, https://github.com/cyschneck/centerline-width/issues
Project-URL: Repository, https://github.com/cyschneck/centerline-width
Keywords: centerline,centerline-detection,centerline-extraction,fluvial,geomorphology,geophysics,hydrology,limnology,networkx,python,river-bank,river-bank-length,rivers,voronoi
Classifier: Development Status :: 4 - Beta
Classifier: Intended Audience :: Developers
Classifier: Intended Audience :: Education
Classifier: Intended Audience :: Science/Research
Classifier: License :: OSI Approved :: MIT License
Classifier: Programming Language :: Python
Classifier: Programming Language :: Python :: 3 :: Only
Classifier: Programming Language :: Python :: 3.10
Classifier: Programming Language :: Python :: 3.11
Classifier: Programming Language :: Python :: 3.12
Classifier: Programming Language :: Python :: 3.13
Classifier: Topic :: Scientific/Engineering :: Hydrology
Classifier: Topic :: Scientific/Engineering :: Physics
Classifier: Topic :: Scientific/Engineering :: Visualization
Requires-Python: >=3.10
License-File: LICENSE
Requires-Dist: geopy
Requires-Dist: haversine
Requires-Dist: matplotlib
Requires-Dist: networkx
Requires-Dist: numpy
Requires-Dist: pandas
Requires-Dist: pykml
Requires-Dist: pyproj
Requires-Dist: scipy
Requires-Dist: shapely
Provides-Extra: dev
Requires-Dist: pre-commit; extra == "dev"
Requires-Dist: pytest; extra == "dev"
Requires-Dist: pytest-cov; extra == "dev"
Dynamic: license-file
